setup.py
statham/__init__.py
statham/tools.py
statham.egg-info/PKG-INFO
statham.egg-info/SOURCES.txt
statham.egg-info/dependency_links.txt
statham.egg-info/top_level.txt