Metadata-Version: 1.0
Name: statham
Version: 0.1
Summary: JSON validator
Home-page: http://google.com
Author: Richard Layte
Author-email: rich.layte@gmail.com
License: UNKNOWN
Platform: UNKNOWN
